{"i":{"VPDVX1Xtgi":{"id":"VPDVX1Xtgi","type":"slide","setup":{"bord":{"size":0,"rad":0},"bg":{"selectedKey":"fill","fill":{"opac":1,"rgb":"var(--TC3)"}},"transparentBg":{"selectedKey":false}}},"KPrFpgj2e":{"id":"KPrFpgj2e","type":"interactive","subtype":"interactiveImage","setup":{"img":{"filt":{"opac":100,"gray":0,"blur":0,"tint":{"rgb":"#FFF","opac":0}},"pos":{"type":"crop","fit":{"bg":{"color":{"rgb":"#FFF","opac":100},"gradient":{"angle":0,"opac":0.5,"stops":[{"color":"#000000","pos":0},{"color":"#000000","pos":100}]}},"vali":"center","hali":"center"},"crop":{"bg":{"color":{"rgb":"#FFF","opac":0},"gradient":{"angle":0,"opac":0.5,"stops":[{"color":"#000000","pos":0},{"color":"#000000","pos":100}]}},"poi":{"x":552,"y":360}},"mask":{"shape":1,"bg":{"color":{"rgb":"#FFF","opac":0},"gradient":{"angle":0,"opac":0.5,"stops":[{"color":"#000000","pos":0},{"color":"#000000","pos":100}]}}}},"measures":{"size":{"width":1080,"height":720}},"orig":{"rType":"asset","rSubType":"image","fileName":"unsplash.jpg","fileSize":0,"val":"mc-73f13e7adac6c842a7c45b4b34388ae3.jpg","aid":"-sW6ZK05HLB"}},"zoom":{"selectedKey":false}}},"mQZjOYYaa":{"id":"mQZjOYYaa","type":"interactive","subtype":"interactiveRichText","setup":{"frmeTp":{"selectedKey":"noneFrame"},"bg":{"selectedKey":"fill","fill":{"opac":0.2,"rgb":"#e0d39d"}},"txt":{"rType":"richtext","val":{"ops":[{"insert":"Photos and figures","attributes":{"color":"#cc5d2b","bold":true}},{"insert":"\n","attributes":{"size":"huge"}},{"insert":"\n\n"},{"insert":"Any photos, images and trademarks used in this course are for non-profit, educational or identification purposes only. Their use does not imply endorsement by FAO. To re-use any materials, please refer to the original copyright holders for terms and conditions of use.","attributes":{"color":"#000000"}},{"insert":"\n\n","attributes":{"size":"normal"}},{"insert":"All pictures are credited to Unsplash except when otherwise specified.","attributes":{"color":"#000000"}},{"insert":"\n\n","attributes":{"size":"normal"}},{"insert":"All graphic and illustrations are credited to the authors except when otherwise specified.","attributes":{"color":"#000000"}},{"insert":"\n","attributes":{"size":"normal"}},{"insert":"\n"}]}},"paddV1":40}}},"v":"1"}