{"i":{"MgW0hsokU":{"id":"MgW0hsokU","type":"slide","setup":{"bg":{"selectedKey":"image","fill":{"opac":1,"rgb":"var(--TC3)"},"img":{"filt":{"opac":100,"gray":0,"blur":0,"tint":{"rgb":"#FFF","opac":0}},"pos":{"type":"crop","fit":{"bg":{"color":{"rgb":"#FFF","opac":100},"gradient":{"angle":0,"opac":0.5,"stops":[{"color":"#000000","pos":0},{"color":"#000000","pos":100}]}},"vali":"center","hali":"center"},"crop":{"bg":{"color":{"rgb":"#FFF","opac":0},"gradient":{"angle":0,"opac":0.5,"stops":[{"color":"#000000","pos":0},{"color":"#000000","pos":100}]}},"poi":{"x":961.5,"y":661.5}},"mask":{"shape":1,"bg":{"color":{"rgb":"#FFF","opac":0},"gradient":{"angle":0,"opac":0.5,"stops":[{"color":"#000000","pos":0},{"color":"#000000","pos":100}]}}}},"measures":{"size":{"width":1923,"height":1364}},"orig":{"rType":"asset","rSubType":"image","fileName":"cover.jpg","fileSize":729746,"val":"mc-8f02f78b1fb91987757b7ff87dd40ef4.jpg","aid":"CGVgCMOHLC"}}},"transparentBg":{"selectedKey":false},"bord":{"size":0,"rad":0}}},"1M3ihVp0h":{"id":"1M3ihVp0h","type":"interactive","subtype":"interactiveLinkedImages","setup":{"imgs":{"i":{"fpstXrIYy":{"type":"image","id":"fpstXrIYy","name":{"rType":"text","val":"Scene 1"},"bg":{"selectedKey":"fill","fill":{"opac":0,"rgb":"#FFF"}},"style":{"selectedKey":"textLabels"},"txtBg":{"fill":{"opac":0.8,"rgb":"#000"}},"imglyrs":{"i":{"XZLn3P3Yk":{"type":"imgLayer","id":"XZLn3P3Yk","name":{"rType":"text","val":"Image layer 1"},"rad":0,"pos":{"x":17,"y":0},"size":{"width":227,"height":65},"bg":{"img":{"filt":{"opac":100,"gray":0,"blur":0,"tint":{"rgb":"#FFF","opac":0}},"pos":{"type":"fit","fit":{"bg":{"color":{"rgb":"#FFF","opac":0},"gradient":{"angle":0,"opac":0.5,"stops":[{"color":"#000000","pos":0},{"color":"#000000","pos":100}]}},"vali":"center","hali":"center"},"crop":{"bg":{"color":{"rgb":"#FFF","opac":0},"gradient":{"angle":0,"opac":0.5,"stops":[{"color":"#000000","pos":0},{"color":"#000000","pos":100}]}},"poi":{"x":186,"y":34.5}},"mask":{"shape":1,"bg":{"color":{"rgb":"#FFF","opac":0},"gradient":{"angle":0,"opac":0.5,"stops":[{"color":"#000000","pos":0},{"color":"#000000","pos":100}]}}}},"measures":{"size":{"width":305,"height":71}},"orig":{"rType":"asset","rSubType":"image","fileName":"Immagine16.png","fileSize":10555,"val":"mc-651e40cbc551d2b80ee078f0ead95a7f.png","aid":"bCR_dqxl27"}}}},"ptqfO_Zjj":{"type":"imgLayer","id":"ptqfO_Zjj","name":{"rType":"text","val":"Image layer 1"},"rad":0,"pos":{"x":271,"y":0},"size":{"width":183,"height":65},"bg":{"img":{"filt":{"opac":100,"gray":0,"blur":0,"tint":{"rgb":"#FFF","opac":0}},"pos":{"type":"fit","fit":{"bg":{"color":{"rgb":"#FFF","opac":0},"gradient":{"angle":0,"opac":0.5,"stops":[{"color":"#000000","pos":0},{"color":"#000000","pos":100}]}},"vali":"center","hali":"center"},"crop":{"bg":{"color":{"rgb":"#FFF","opac":0},"gradient":{"angle":0,"opac":0.5,"stops":[{"color":"#000000","pos":0},{"color":"#000000","pos":100}]}},"poi":{"x":364.5,"y":87}},"mask":{"shape":1,"bg":{"color":{"rgb":"#FFF","opac":0},"gradient":{"angle":0,"opac":0.5,"stops":[{"color":"#000000","pos":0},{"color":"#000000","pos":100}]}}}},"measures":{"size":{"width":783,"height":174}},"orig":{"rType":"asset","rSubType":"image","fileName":"Central Eastern Europe - White text.png","fileSize":23009,"val":"mc-d43e87c7e149b3db21eff53c2a5abd4e.png","aid":"93sdt3t4sM"}}}}},"p":["XZLn3P3Yk","ptqfO_Zjj"]},"t":{"i":{"Ta79gv_JE":{"type":"text","id":"Ta79gv_JE","pos":{"x":28,"y":162},"style":{"selectedKey":"noBoxed"},"size":{"selectedKey":321},"color":{"opac":1,"rgb":"#FFF"},"desc":{"rType":"richtext","val":{"ops":[{"insert":"E-LEARNING COURSE","attributes":{"color":"var(--TC3)"}},{"insert":"\n","attributes":{"size":"large"}}]}}},"C_jFJqnMH":{"type":"text","id":"C_jFJqnMH","pos":{"x":28,"y":367},"style":{"selectedKey":"noBoxed"},"size":{"selectedKey":523},"color":{"opac":1,"rgb":"#FFF"},"desc":{"rType":"richtext","val":{"ops":[{"insert":"Integrating gender equality and social inclusion in national drought management planning","attributes":{"bold":true,"color":"var(--TC3)"}},{"insert":"\n","attributes":{"size":"huge"}}]},"hali":""}},"Gjc3V_07o":{"type":"text","id":"Gjc3V_07o","pos":{"x":17,"y":928},"style":{"selectedKey":"noBoxed"},"size":{"selectedKey":563},"color":{"opac":1,"rgb":"#FFF"},"desc":{"rType":"richtext","val":{"ops":[{"insert":"developed in collaboration with GWP CEE and Integrated Drought Management Programme","attributes":{"color":"var(--TC3)","italic":true}},{"insert":"\n","attributes":{"size":"small"}}]},"hali":""}}},"p":["Ta79gv_JE","Gjc3V_07o","C_jFJqnMH"]}}},"p":["fpstXrIYy"]}}},"uKB3zlmK6m":{"id":"uKB3zlmK6m","type":"interactive","subtype":"interactiveRichText","setup":{"frmeTp":{"selectedKey":"noneFrame"},"bg":{"selectedKey":"fill","fill":{"opac":0,"rgb":"#FFF"}},"txt":{"rType":"richtext","val":{"ops":[{"insert":"Integrating Gender Equality and Social Inclusion in national drought management planning","attributes":{"color":"#ffffff","bold":true}},{"insert":"\n","attributes":{"size":"huge"}}]}},"vali":"top","paddV1":35}}},"v":"1"}